{
    "myrows": [{
        "rank": "1",
        "team": "TEAM SKY",
        "times": "48' 31''",
        "gap": "&nbsp;"
    }, {
        "rank": "2",
        "team": "QUICK - STEP FLOORS",
        "times": "49' 08''",
        "gap": "+ 00' 37''"
    }, {
        "rank": "3",
        "team": "TEAM SUNWEB",
        "times": "49' 29''",
        "gap": "+ 00' 58''"
    }, {
        "rank": "4",
        "team": "TEAM LOTTO NL - JUMBO",
        "times": "49' 32''",
        "gap": "+ 01' 01''"
    }, {
        "rank": "5",
        "team": "TEAM KATUSHA ALPECIN",
        "times": "49' 32''",
        "gap": "+ 01' 01''"
    }, {
        "rank": "6",
        "team": "BMC RACING TEAM",
        "times": "49' 38''",
        "gap": "+ 01' 07''"
    }, {
        "rank": "7",
        "team": "MOVISTAR TEAM",
        "times": "49' 39''",
        "gap": "+ 01' 08''"
    }, {
        "rank": "8",
        "team": "BORA - HANSGROHE",
        "times": "49' 50''",
        "gap": "+ 01' 19''"
    }, {
        "rank": "9",
        "team": "ORICA - SCOTT",
        "times": "49' 50''",
        "gap": "+ 01' 19''"
    }, {
        "rank": "10",
        "team": "ASTANA PRO TEAM",
        "times": "49' 50''",
        "gap": "+ 01' 19''"
    }, {
        "rank": "11",
        "team": "CANNONDALE DRAPAC PROFESSIONAL CYCLING TEAM",
        "times": "50' 02''",
        "gap": "+ 01' 31''"
    }, {
        "rank": "12",
        "team": "TREK - SEGAFREDO",
        "times": "50' 26''",
        "gap": "+ 01' 55''"
    }, {
        "rank": "13",
        "team": "AG2R LA MONDIALE",
        "times": "50' 30''",
        "gap": "+ 01' 59''"
    }, {
        "rank": "14",
        "team": "TEAM DIMENSION DATA",
        "times": "50' 33''",
        "gap": "+ 02' 02''"
    }, {
        "rank": "15",
        "team": "FDJ",
        "times": "50' 37''",
        "gap": "+ 02' 06''"
    }, {
        "rank": "16",
        "team": "LOTTO SOUDAL",
        "times": "50' 40''",
        "gap": "+ 02' 09''"
    }, {
        "rank": "17",
        "team": "DIRECT ENERGIE",
        "times": "50' 43''",
        "gap": "+ 02' 12''"
    }, {
        "rank": "18",
        "team": "BAHRAIN - MERIDA",
        "times": "51' 07''",
        "gap": "+ 02' 36''"
    }, {
        "rank": "19",
        "team": "UAE TEAM EMIRATES",
        "times": "51' 14''",
        "gap": "+ 02' 43''"
    }, {
        "rank": "20",
        "team": "TEAM FORTUNEO - OSCARO",
        "times": "51' 24''",
        "gap": "+ 02' 53''"
    }, {
        "rank": "21",
        "team": "COFIDIS, SOLUTIONS CREDITS",
        "times": "51' 27''",
        "gap": "+ 02' 56''"
    }, {
        "rank": "22",
        "team": "WANTY - GROUPE GOBERT",
        "times": "52' 21''",
        "gap": "+ 03' 50''"
    }]
}